nonebot_plugin_baidutranslate/__init__.py
nonebot_plugin_baidutranslate/config.py
nonebot_plugin_baidutranslate/consts.py
nonebot_plugin_baidutranslate/data_source.py
nonebot_plugin_baidutranslate/exceptions.py
nonebot_plugin_baidutranslate-0.3.2.dist-info/LICENSE
nonebot_plugin_baidutranslate-0.3.2.dist-info/METADATA
nonebot_plugin_baidutranslate-0.3.2.dist-info/WHEEL
nonebot_plugin_baidutranslate-0.3.2.dist-info/top_level.txt
nonebot_plugin_baidutranslate-0.3.2.dist-info/RECORD
