Metadata-Version: 2.1
Name: nonebot-plugin-baidutranslate
Version: 0.3.2
Summary: 基于 OneBot 适配器的 NoneBot2 百度翻译插件, 可以调用百度翻译 API 实现常用语种之间的互译
Home-page: https://github.com/NumberSir/nonebot_plugin_baidutranslate
Author: Number_Sir
Author-email: Number_Sir@126.com
Keywords: pip,nonebot2,nonebot,nonebot_plugin
Platform: any
Classifier: Programming Language :: Python :: 3
Classifier: License :: OSI Approved :: MIT License
Classifier: Operating System :: OS Independent
Requires-Python: >=3.8
License-File: LICENSE
Requires-Dist: nonebot-adapter-onebot (>=2.2.1)
Requires-Dist: nonebot2 (>=2.0.0rc3)
Requires-Dist: httpx (>=0.22.0)
